{
    "_fetched_at": "2024-08-08T00:56:35Z",
    "name_ja": "韓国語Ⅰ",
    "name_en": "Korean Language I",
    "syllabus_number": "1004300A",
    "course_number": "00FL102",
    "target_departments_and_courses": [
        "経済学部",
        "福祉情報学部"
    ],
    "type": "総合科目",
    "main_department": "",
    "requirements": "選択科目",
    "year": 1,
    "period": "",
    "required_or_elective": "",
    "course_category": "",
    "class_type": "単独",
    "teachers": [
        {
            "name": "李　萬善",
            "main": false
        }
    ],
    "term": "後期",
    "credits": 2,
    "teaching_methods": [
        "講義"
    ],
    "class_forms": [
        "対面"
    ],
    "themes_and_goals": "世界的視野と広く豊かな教養持つ人材を育成するためには、他言語の習得が求められる。英語以外の外国語として韓国語は、学びやすく実用的だ。韓国語を理解することにより、ネット上の様々な情報を日本語に限らず、韓国語で収集分析できるようになる。また、和訳ではわからない、韓国語ならではのニュアンスに気づくこともできる。韓国語を話せるようになると、韓国人と話す機会も増え、交流も深められる。その過程で視野を広げることが出来、多様な価値観を尊重する人材になることができる。\n\n【到達目標】\n基本的な挨拶や会話が聞き取れ、それに応答できる。\n日本と韓国の文化、習慣などの違いを知り、理解を深める。\n各ユニットの対話部分が、正しく音読できる。\n韓国語の会話表現に慣れ、自然な会話につなげる。",
    "overview": "教科書に沿って授業を展開する。ペアワークを多用し、発話の機会を増やし、十分会話の練習をするようにする。表現や文法学習で、練習問題があるので、必ずノートを準備し、問題を解くようにする。韓国の行事や習慣など、適時紹介する。",
    "corresponding_diploma_policies": [],
    "textbooks": [
        {
            "title": "（チュクチュクチャラネ）ぐんぐん伸びる韓国語　初級",
            "year": 2022,
            "author": "朴恩珠　森類臣　権世美",
            "publisher": "白帝社",
            "price": 2640,
            "isbn": "9784863984561",
            "available_on_campus": true
        }
    ],
    "reference_books": [],
    "notes_on_enrollment": {
        "required_courses": [],
        "recommended_courses": [],
        "brings": "教科書、筆記用具、ノート",
        "other": "定員を40名とする。履修希望者が40名を超えた場合は抽選により決定する。"
    },
    "evaluation_criteria": "語彙、表現、文法等の理解、授業内で行われる音読、日本語で作成されたレポートによる評価をする。",
    "evaluation_ratio": {
        "試験": 60,
        "小テスト": 20,
        "レポート": 20,
        "発表・実技": 0,
        "ポートフォリオ": 0,
        "その他": 0
    },
    "message_from_teachers": "入門や初級の学習において、文字や文法の習得に時間を取られ、会話ができるレベルにまで至らないことがあります。このテキストでは、文法学習のための練習問題を解くのに、従来のように時間をかけるのではなく、実用的な会話表現が定着できるようにします。\n語学の学習は、復習が大切です。また、語学学習において音読の練習はとても大切です。小テストに含まれることもありますので、普段から音読をしましょう。音声はダウンロードできますので、保存して何度も聞きましょう。",
    "schedule": [
        {
            "session": "１",
            "content": "オリエンテーション\n第一部\n1課　母音字１　挨拶",
            "methods": [
                "講義"
            ],
            "teachers": [
                "李　萬善"
            ]
        },
        {
            "session": "２",
            "content": "2課　子音字１\n平音１（初声）　平音２（終声）",
            "methods": [
                "講義"
            ],
            "teachers": [
                "李　萬善"
            ]
        },
        {
            "session": "３",
            "content": "３課　母音字２\n自己紹介",
            "methods": [
                "講義"
            ],
            "teachers": [
                "李　萬善"
            ]
        },
        {
            "session": "４",
            "content": "４課　子音字２　（初声）\n激音（初声）",
            "methods": [
                "講義"
            ],
            "teachers": [
                "李　萬善"
            ]
        },
        {
            "session": "５",
            "content": "５課　バッチム　（終声）",
            "methods": [
                "講義"
            ],
            "teachers": [
                "李　萬善"
            ]
        },
        {
            "session": "６",
            "content": "１課－５課　復習",
            "methods": [
                "講義"
            ],
            "teachers": [
                "李　萬善"
            ]
        },
        {
            "session": "７",
            "content": "６課　母音字３",
            "methods": [
                "講義"
            ],
            "teachers": [
                "李　萬善"
            ]
        },
        {
            "session": "８",
            "content": "７課　子音字母\n日本語のハングル表現",
            "methods": [
                "講義"
            ],
            "teachers": [
                "李　萬善"
            ]
        },
        {
            "session": "９",
            "content": "８課　教室でよく使う表現\n発音のきまり",
            "methods": [
                "講義"
            ],
            "teachers": [
                "李　萬善"
            ]
        },
        {
            "session": "１０",
            "content": "１課－８課　復習",
            "methods": [
                "講義"
            ],
            "teachers": [
                "李　萬善"
            ]
        },
        {
            "session": "１１",
            "content": "ソウル旅行プラン作成\n韓国についてもっと知ろう。",
            "methods": [
                "講義"
            ],
            "teachers": [
                "李　萬善"
            ]
        },
        {
            "session": "１２",
            "content": "第二部\n１課　あいさつ、友人紹介",
            "methods": [
                "講義"
            ],
            "teachers": [
                "李　萬善"
            ]
        },
        {
            "session": "１３",
            "content": "２課　これは何ですか？（コンビニで）\n指示語",
            "methods": [
                "講義"
            ],
            "teachers": [
                "李　萬善"
            ]
        },
        {
            "session": "１４",
            "content": "３課　～ありますか。（コーヒーショップで）\n存在詞、ハムニダ体",
            "methods": [
                "講義"
            ],
            "teachers": [
                "李　萬善"
            ]
        },
        {
            "session": "１５",
            "content": "４課　いくらですか。（服屋で）\n漢数詞、電話番号、年月日、誕生日",
            "methods": [
                "講義"
            ],
            "teachers": [
                "李　萬善"
            ]
        },
        {
            "session": "１６",
            "content": "５課　～をください　（店で）\n固有数詞、助数詞、時間、年齢",
            "methods": [
                "講義"
            ],
            "teachers": [
                "李　萬善"
            ]
        },
        {
            "session": "１７",
            "content": "６課　どこに行きますか。\nヘヨ形、並列表現",
            "methods": [
                "講義"
            ],
            "teachers": [
                "李　萬善"
            ]
        },
        {
            "session": "１８",
            "content": "７課　～しません、否定形、　年、月、曜日、\n～が好きです、～ですね",
            "methods": [
                "講義"
            ],
            "teachers": [
                "李　萬善"
            ]
        },
        {
            "session": "１９",
            "content": "８課　ヘヨ形とハムニダ形の過去形、\n原因・理由、不規則活用",
            "methods": [
                "講義"
            ],
            "teachers": [
                "李　萬善"
            ]
        },
        {
            "session": "２０",
            "content": "９課　～したい　願望、比較表現",
            "methods": [
                "講義"
            ],
            "teachers": [
                "李　萬善"
            ]
        },
        {
            "session": "２１",
            "content": "１０課　～しに行く、～しようとする\n～だが、～ですよね",
            "methods": [
                "講義"
            ],
            "teachers": [
                "李　萬善"
            ]
        },
        {
            "session": "２２",
            "content": "１１課　～から～まで、丁寧な命令・指示、\n条件・仮定、不規則活用",
            "methods": [
                "講義"
            ],
            "teachers": [
                "李　萬善"
            ]
        },
        {
            "session": "２３",
            "content": "１２課　可能・不可能表現、必要・義務表現",
            "methods": [
                "講義"
            ],
            "teachers": [
                "李　萬善"
            ]
        },
        {
            "session": "２４",
            "content": "１３課　提案・勧誘、～しましょうか",
            "methods": [
                "講義"
            ],
            "teachers": [
                "李　萬善"
            ]
        },
        {
            "session": "２５",
            "content": "１４課　遺失物センタ―で\n意志・約束、動詞の連体形、",
            "methods": [
                "講義"
            ],
            "teachers": [
                "李　萬善"
            ]
        },
        {
            "session": "２６",
            "content": "１５課　電話で、予定・意志・推測表現、形容詞・存在詞・指定詞の連体形",
            "methods": [
                "講義"
            ],
            "teachers": [
                "李　萬善"
            ]
        },
        {
            "session": "２７",
            "content": "１６課　～してみてください、行為の勧め、原因・理由表現",
            "methods": [
                "講義"
            ],
            "teachers": [
                "李　萬善"
            ]
        },
        {
            "session": "２８",
            "content": "１７課　ホテルで、～してください、依頼表現、不規則活用、病状を表す表現",
            "methods": [
                "講義"
            ],
            "teachers": [
                "李　萬善"
            ]
        },
        {
            "session": "２９",
            "content": "１８課　日本の空港で、尊敬の接尾辞、不規則活用",
            "methods": [
                "講義"
            ],
            "teachers": [
                "李　萬善"
            ]
        },
        {
            "session": "３０",
            "content": "１９課　冬休みにしたこと、動作の継続表現、状態・状態の継続表現",
            "methods": [
                "講義"
            ],
            "teachers": [
                "李　萬善"
            ]
        }
    ],
    "open_to_non_students": true,
    "practitioner": ""
}
