{
    "_fetched_at": "2024-08-08T01:04:40Z",
    "name_ja": "専門ゼミⅡ",
    "name_en": "Academic Seminar II",
    "syllabus_number": "2007700O",
    "course_number": "10SE401、05HS401",
    "target_departments_and_courses": [
        "福祉情報学部"
    ],
    "type": "専門科目",
    "main_department": "福祉情報学部",
    "requirements": "必修科目",
    "year": 4,
    "period": "",
    "required_or_elective": "",
    "course_category": "",
    "class_type": "単独",
    "teachers": [
        {
            "name": "羽渕　由子",
            "main": false
        }
    ],
    "term": "通年",
    "credits": 4,
    "teaching_methods": [
        "演習"
    ],
    "class_forms": [
        "対面"
    ],
    "themes_and_goals": "以下の３つの教育目標を掲げる授業科目である。\n（１）人間の行動メカニズムや認知的特性について基礎的な知識を有しており、必要に応じて問題設定を行い、\nそれを解決するに足る研究基礎能力（情報収集、データ解析、資料化）を身に着けている。【知識及び技能】\n（２）仮説演繹的な思考力を備え、問題解決の過程を科学論文としてまとめることができる。また、それらを\n口演等の手段で的確にプレゼンテーションする技術を備えている。 【思考力・判断力・表現力等】\n（３）実社会の中で、自ら問題を発見・定義し、その解決に向けて主体的に行動を起こすことができる。また、\nその過程において、多様な文化・社会的基盤を持つ他者と適切に協働することができる。【主体性・多様性・協調性】\n（４）グローバルな視野をもって地域を見つめ、広く豊かな教養と高いEQを活かしたアクティブ・ラーナーと\nして、地域の持続的な発展に貢献できる。 【地域貢献】",
    "overview": "専門ゼミⅠで身につけた基礎的知識とスキルを活かして、自分の興味・関心のあるテーマについて科学的に検証し、卒業論文としてまとめる。受講生は関連領域の研究資料を読み、それぞれが興味を持つ研究トピックについてデータを収集して分析をおこなう。発表資料作成、発表、ディスカッション、卒業論文の執筆を通して学士としての基礎知識やスキルを修得することをねらいとする。",
    "corresponding_diploma_policies": [
        "知識及び技能の習得",
        "思考力・判断力・表現力等の養成",
        "主体性・多様性・協調性の養成",
        "地域貢献に関する意識の醸成"
    ],
    "textbooks": [],
    "reference_books": [
        {
            "title": "心理学の卒業研究ワークブック ――発想から論文完成までの10ステージーー",
            "year": 2015,
            "author": "小塩真司・宅香菜子",
            "publisher": "金子書房",
            "price": 2750,
            "isbn": "4760826556",
            "available_on_campus": false
        }
    ],
    "notes_on_enrollment": {
        "required_courses": [],
        "recommended_courses": [
            "心理学研究法Ⅰ",
            "心理学研究法Ⅱ",
            "心理学実験実習Ⅰ",
            "心理学実験実習Ⅱ",
            "心理学概論Ⅰ",
            "心理学概論Ⅱ"
        ],
        "brings": "ノートパソコン，筆記用具",
        "other": ""
    },
    "evaluation_criteria": "以下の観点から評価する。\n（ⅰ）研究の過程と成果を表現したり評価したりする能力・技能\n（ⅱ）研究課題を発見し、適切な研究計画を立案する能力・技能\n（ⅲ）得られたデータに基づいて分析をおこない、論文としてまとめる能力・技能",
    "evaluation_ratio": {
        "試験": 0,
        "小テスト": 0,
        "レポート": 40,
        "発表・実技": 40,
        "ポートフォリオ": 20,
        "その他": 0
    },
    "message_from_teachers": "大学生の学びの集大成である卒業論文の執筆に向けて、自らの興味・関心・問題意識に基づいて時間をかけてテーマを決め、計画を立案しましょう。主体的・自律的な取り組みを期待します。\n各自が自分の興味のあるテーマについて調べたことを発表します。実験や調査データをとったら，分析結果を発表して意見交換をします。４年生後期から卒論にまとめます。",
    "schedule": [
        {
            "session": "1",
            "content": "卒業研究テーマの検討（１）：研究テーマを決定する／自分の興味・関心のあるテーマについて調べ、先行研究の情報を収集する",
            "methods": [
                "演習"
            ],
            "teachers": [
                "羽渕　由子"
            ]
        },
        {
            "session": "2",
            "content": "卒業研究テーマの検討（２）：先行研究１をまとめる／自分の興味・関心のあるテーマについて調べ、先行研究１の概要と問題点をまとめる",
            "methods": [
                "演習"
            ],
            "teachers": [
                "羽渕　由子"
            ]
        },
        {
            "session": "3",
            "content": "卒業研究テーマの検討（３）：先行研究２をまとめる／自分の興味・関心のあるテーマについて調べ、先行研究２の概要と問題点をまとめる",
            "methods": [
                "演習"
            ],
            "teachers": [
                "羽渕　由子"
            ]
        },
        {
            "session": "4",
            "content": "卒業研究テーマの検討（４）：先行研究をまとめ，問題と目的を明らかにする／先行研究の概要と問題点をまとめる",
            "methods": [
                "演習"
            ],
            "teachers": [
                "羽渕　由子"
            ]
        },
        {
            "session": "5",
            "content": "卒業研究テーマの検討（５）：自分自身の研究テーマの仮説を設定する／自分の研究テーマの仮説を設定する",
            "methods": [
                "演習"
            ],
            "teachers": [
                "羽渕　由子"
            ]
        },
        {
            "session": "6",
            "content": "実施計画の検討と準備（１）：調査・実験の計画を立てる／具体的な研究計画をまとめ、実施の準備をする",
            "methods": [
                "演習"
            ],
            "teachers": [
                "羽渕　由子"
            ]
        },
        {
            "session": "7",
            "content": "研究実施計画の検討と準備（２）：調査・実験の材料を作成する／具体的な研究計画に基づき，調査・実験の材料を準備する",
            "methods": [
                "演習"
            ],
            "teachers": [
                "羽渕　由子"
            ]
        },
        {
            "session": "8",
            "content": "研究実施計画の検討と準備（３）：調査・実験の手続きを検討する／具体的な研究計画に基づき，調査・実験の手続きを確定する",
            "methods": [
                "演習"
            ],
            "teachers": [
                "羽渕　由子"
            ]
        },
        {
            "session": "9",
            "content": "研究実施計画の検討と準備（４）：調査・実験の依頼をする／具体的な研究計画に基づき，調査・実験の依頼をする",
            "methods": [
                "演習"
            ],
            "teachers": [
                "羽渕　由子"
            ]
        },
        {
            "session": "10",
            "content": "実験・調査実施（１）：調査・実験を実施する／調査・実験をおこない，データを取得する",
            "methods": [
                "演習"
            ],
            "teachers": [
                "羽渕　由子"
            ]
        },
        {
            "session": "11",
            "content": "実験・調査実施（２）：調査・実験を実施する／調査・実験をおこない，データを取得する",
            "methods": [
                "演習"
            ],
            "teachers": [
                "羽渕　由子"
            ]
        },
        {
            "session": "12",
            "content": "実験・調査実施（３）：調査・実験を実施する／調査・実験をおこない，データを取得する",
            "methods": [
                "演習"
            ],
            "teachers": [
                "羽渕　由子"
            ]
        },
        {
            "session": "13",
            "content": "実験・調査実施（４）：調査・実験を実施する／調査・実験をおこない，データを取得する",
            "methods": [
                "演習"
            ],
            "teachers": [
                "羽渕　由子"
            ]
        },
        {
            "session": "14",
            "content": "データ分析（１）：調査・実験のデータを整理する／調査・実験で得られたデータを整理する",
            "methods": [
                "演習"
            ],
            "teachers": [
                "羽渕　由子"
            ]
        },
        {
            "session": "15",
            "content": "データ分析（２）：調査・実験のデータを整理する／調査・実験で得られたデータを整理する",
            "methods": [
                "演習"
            ],
            "teachers": [
                "羽渕　由子"
            ]
        },
        {
            "session": "16",
            "content": "データ分析（３）：調査・実験のデータを分析する／調査・実験で得られたデータを分析する",
            "methods": [
                "演習"
            ],
            "teachers": [
                "羽渕　由子"
            ]
        },
        {
            "session": "17",
            "content": "データ分析（４）：調査・実験のデータを分析する／調査・実験で得られたデータを分析する",
            "methods": [
                "演習"
            ],
            "teachers": [
                "羽渕　由子"
            ]
        },
        {
            "session": "18",
            "content": "結果の考察（１）：分析結果を考察する／調査・実験で得られたデータを考察する",
            "methods": [
                "演習"
            ],
            "teachers": [
                "羽渕　由子"
            ]
        },
        {
            "session": "19",
            "content": "結果の考察（２）：分析結果を考察する／調査・実験で得られたデータを考察する",
            "methods": [
                "演習"
            ],
            "teachers": [
                "羽渕　由子"
            ]
        },
        {
            "session": "20",
            "content": "結果のまとめ（１）：分析結果をまとめる／調査・実験の結果をまとめる",
            "methods": [
                "演習"
            ],
            "teachers": [
                "羽渕　由子"
            ]
        },
        {
            "session": "21",
            "content": "結果のまとめ（２）：分析結果をまとめる／調査・実験の結果をまとめる",
            "methods": [
                "演習"
            ],
            "teachers": [
                "羽渕　由子"
            ]
        },
        {
            "session": "22",
            "content": "卒業論文執筆（１）：「方法」を書く／卒業論文の「方法」を執筆する",
            "methods": [
                "演習"
            ],
            "teachers": [
                "羽渕　由子"
            ]
        },
        {
            "session": "23",
            "content": "卒業論文執筆（２）：「結果」を書く／卒業論文の「結果」を執筆する",
            "methods": [
                "演習"
            ],
            "teachers": [
                "羽渕　由子"
            ]
        },
        {
            "session": "24",
            "content": "卒業論文執筆（３）：「問題と目的」を書く／卒業論文の「問題と目的」を執筆する",
            "methods": [
                "演習"
            ],
            "teachers": [
                "羽渕　由子"
            ]
        },
        {
            "session": "25",
            "content": "卒業論文執筆（４）：「考察」を書く／卒業論文の「考察」を執筆する",
            "methods": [
                "演習"
            ],
            "teachers": [
                "羽渕　由子"
            ]
        },
        {
            "session": "26",
            "content": "卒業論文執筆（５）：「要旨」「引用文献」「目次」「まえがき」「あとがき」を完成させる／卒業論文を完成させる",
            "methods": [
                "演習"
            ],
            "teachers": [
                "羽渕　由子"
            ]
        },
        {
            "session": "27",
            "content": "卒業論文の校閲（１）／卒業論文を推敲する\n卒業研究発表会準備（１）：発表資料を作成する／卒業研究発表会に向けて発表資料を作成する",
            "methods": [
                "演習"
            ],
            "teachers": [
                "羽渕　由子"
            ]
        },
        {
            "session": "28",
            "content": "卒業論文の校閲（２）／卒業論文の誤字脱字をチェックする\n卒業研究発表会準備（２）：卒業論文発表会の予行練習をする／卒業研究発表会に向けて発表資料を作成する",
            "methods": [
                "演習"
            ],
            "teachers": [
                "羽渕　由子"
            ]
        },
        {
            "session": "29",
            "content": "卒業研究発表会／卒業研究発表会に向けて配布資料を作成する",
            "methods": [
                "演習"
            ],
            "teachers": [
                "羽渕　由子"
            ]
        },
        {
            "session": "30",
            "content": "卒業論文概要集の原稿をまとめる／卒業論文を製本する，卒業論文概要集の原稿を提出する",
            "methods": [
                "演習"
            ],
            "teachers": [
                "羽渕　由子"
            ]
        }
    ],
    "open_to_non_students": false,
    "practitioner": ""
}
