{
    "_fetched_at": "2024-08-08T01:22:09Z",
    "name_ja": "国際政治経済学Ⅱ",
    "name_en": "International Political Economy II",
    "syllabus_number": "2042600A",
    "course_number": "01TE302",
    "target_departments_and_courses": [
        "経済学部"
    ],
    "type": "専門科目",
    "main_department": "経済学部",
    "requirements": "選択科目",
    "year": 3,
    "period": "",
    "required_or_elective": "",
    "course_category": "",
    "class_type": "単独",
    "teachers": [
        {
            "name": "岡本　次郎",
            "main": false
        }
    ],
    "term": "後期",
    "credits": 2,
    "teaching_methods": [
        "講義"
    ],
    "class_forms": [
        "対面"
    ],
    "themes_and_goals": "本授業は，「国際政治経済学Ⅰ」で学習した内容を基礎として，多様な国際政治経済問題をより深く理解することをテーマとする。\n\n【到達目標】以下を学び，説明できるようになること。\n(1)現代の国際政治経済課題を説明するための専門的な概念・用語\n(2)現代の国際政治経済における多様な課題\n(3)グローバル・ガバナンスの概念と，それが諸課題の制御・解決のためにどのように用いられているか",
    "overview": "本授業でとりあげる国際政治経済問題は，貿易，国際金融，人の移動（移民・難民），経済発展と人権・民主化，環境問題などである。また，国際社会がこれらの諸課題をどのように制御・解決しようとしているのかについて，グローバル・ガバナンスの観点から説明する。",
    "corresponding_diploma_policies": [
        "知識及び技能の習得",
        "思考力・判断力・表現力等の養成"
    ],
    "textbooks": [],
    "reference_books": [
        {
            "title": "『国際政治経済学・入門』第3版",
            "year": 2007,
            "author": "野林健・大芝亮・納家正嗣・山田敦・長尾悟",
            "publisher": "有斐閣アルマ",
            "price": 2200,
            "isbn": "4641123330",
            "available_on_campus": false
        },
        {
            "title": "国際政治経済",
            "year": 2007,
            "author": "飯田敬輔",
            "publisher": "東京大学出版会",
            "price": 2500,
            "isbn": "4130342533",
            "available_on_campus": false
        }
    ],
    "notes_on_enrollment": {
        "required_courses": [
            "国際政治経済学Ⅰ"
        ],
        "recommended_courses": [],
        "brings": "自分で印刷した講義資料、または講義資料をダウンロードしたPCあるいはタブレット。",
        "other": "特定の教科書は使用しない。毎週，講義資料をアップロードする。"
    },
    "evaluation_criteria": "【到達目標】に記載した事項の理解度を「学生に対する評価」の内容で評価する。「その他」は授業中に複数回提示する課題への回答で評価する。中間レポートと定期試験「両方」の提出・受験を成績評価を受けるための必要条件とするので留意すること。また，受講生の人数によって成績評価方法の変更を行う可能性があり，その際には授業等で周知する。",
    "evaluation_ratio": {
        "試験": 40,
        "小テスト": 0,
        "レポート": 40,
        "発表・実技": 0,
        "ポートフォリオ": 0,
        "その他": 20
    },
    "message_from_teachers": "グローバル化が進む現代では，世界的な政治経済環境とその変化の影響を受けずに行動できる国家はきわめて少ない。最近の例としては，コロナウィルスによるパンデミックやロシアのウクライナ侵攻が挙げられるだろう。本授業では，貿易，国際金融，人の国際移動（移民・難民），経済発展と民主化・人権，地球環境等を取り上げ，これらのイシューがどのように諸国家に影響を与えるのかを説明する。授業では受講生に小さな「問い」を多く投げかけるので，積極的に応えて欲しい。\n\n【予習・復習について】\n授業に先立って講義資料をアップロードする。受講生は毎週次の授業の講義資料を印刷（またはダウンロード）し，予習を行うこと。授業後は講義資料を読み返し，学習内容の定着を図ること。",
    "schedule": [
        {
            "session": "1",
            "content": "イントロダクション:講義の進め方，評価方法・基準などの説明。",
            "methods": [
                "講義"
            ],
            "teachers": [
                "岡本　次郎"
            ]
        },
        {
            "session": "2",
            "content": "「国際政治経済学Ⅰの復習：なぜ国家は国際協力をするのか？　第2次世界大戦後の国際経済体制とその展開。",
            "methods": [
                "講義"
            ],
            "teachers": [
                "岡本　次郎"
            ]
        },
        {
            "session": "3",
            "content": "国際経済体制と経済安全保障：経済「力」について（経済制裁，天然資源など），産業政策と経済安全保障，国際経済体制の維持と変更",
            "methods": [
                "講義"
            ],
            "teachers": [
                "岡本　次郎"
            ]
        },
        {
            "session": "4",
            "content": "貿易をめぐる政治と経済 (1)：自由貿易とは何か，GATT/WTOの役割，貿易交渉",
            "methods": [
                "講義"
            ],
            "teachers": [
                "岡本　次郎"
            ]
        },
        {
            "session": "5",
            "content": "貿易をめぐる政治と経済 (2)：国際競争力の盛衰，保護主義の論理，貿易摩擦とその対応",
            "methods": [
                "講義"
            ],
            "teachers": [
                "岡本　次郎"
            ]
        },
        {
            "session": "6",
            "content": "国際金融をめぐる政治と経済：ブレトンウッズ体制，情報通信技術革命と金融グローバル化，金融（債務，通貨）危機，タックス・ヘイブン，グローバル・タックス",
            "methods": [
                "講義"
            ],
            "teachers": [
                "岡本　次郎"
            ]
        },
        {
            "session": "7",
            "content": "人の移動と国際政治経済 (1)：移民とは誰か，難民とは誰か？　増加する移民・難民，移民・難民を受け入れる制度，排斥される移民・難民",
            "methods": [
                "講義"
            ],
            "teachers": [
                "岡本　次郎"
            ]
        },
        {
            "session": "8",
            "content": "人の移動と国際政治経済 (2)：少子高齢化する日本社会，日本への移民と「外国人労働者」，外国人労働者を受け入れる制度，外国人労働の現実",
            "methods": [
                "講義"
            ],
            "teachers": [
                "岡本　次郎"
            ]
        },
        {
            "session": "9",
            "content": "経済発展と人権・民主化 (1)：先進国と途上国，経済発展とは何か？　国連と世界銀行，経済発展と人権尊重・民主化は相関するのか？",
            "methods": [
                "講義"
            ],
            "teachers": [
                "岡本　次郎"
            ]
        },
        {
            "session": "10",
            "content": "経済発展と人権，民主化 (2)：経済グローバル化と人権・民主化，人間の安全保障，ビジネスと法，MDGs/SDGs",
            "methods": [
                "講義"
            ],
            "teachers": [
                "岡本　次郎"
            ]
        },
        {
            "session": "11",
            "content": "地球環境と国際政治経済 (1)：負の外部性，公害問題から環境問題へ，越境する環境問題",
            "methods": [
                "講義"
            ],
            "teachers": [
                "岡本　次郎"
            ]
        },
        {
            "session": "12",
            "content": "地球環境と国際政治経済 (2)：国際環境問題，企業の社会的責任，「グローバル・コモンズ」，国際環境ガバナンス",
            "methods": [
                "講義"
            ],
            "teachers": [
                "岡本　次郎"
            ]
        },
        {
            "session": "13",
            "content": "「経済グローバル化」再考：経済グローバル化とは何か？　グローバル化の問題点，国際政治と国際経済の相克",
            "methods": [
                "講義"
            ],
            "teachers": [
                "岡本　次郎"
            ]
        },
        {
            "session": "14",
            "content": "国際経済秩序の再構築 (1)：グローバルレベルでの再構築（WTO改革），地域レベルでの再構築（自由貿易協定），大国による一方的再構築の試み",
            "methods": [],
            "teachers": [
                "岡本　次郎"
            ]
        },
        {
            "session": "15",
            "content": "国際経済秩序の再構築 (2)：並行する再構築の試み，大国のリーダーシップ・中小国のフォロワーシップ，なぜ何を維持し何を変更するのか？",
            "methods": [
                "講義"
            ],
            "teachers": [
                "岡本　次郎"
            ]
        }
    ],
    "open_to_non_students": true,
    "practitioner": ""
}
