{
    "_fetched_at": "2024-08-07T15:55:18Z",
    "name_ja": "専門ゼミⅠ",
    "name_en": "Seminar on Specialized Subjects I",
    "syllabus_number": "2007600EE",
    "course_number": "",
    "target_departments_and_courses": [
        "経済学部"
    ],
    "type": "",
    "main_department": "",
    "requirements": "",
    "year": 3,
    "period": "",
    "required_or_elective": "※設定中",
    "course_category": "",
    "class_type": "単独",
    "teachers": [
        {
            "name": "岡本　次郎",
            "main": false
        }
    ],
    "term": "通年",
    "credits": 4,
    "teaching_methods": [
        "演習"
    ],
    "class_forms": [
        "対面"
    ],
    "themes_and_goals": "本ゼミのテーマは、日々の生活に影響をもたらす国際政治経済事象に関心を持つこと、卒業論文執筆の準備をすることである。\n\n【到達目標】\n①国際政治経済学の理論と歴史を学び、現実に起こる国際政治経済事象の説明ができるようになる。\n②学術的論文とは何かを学び、その構造、作法等を理解する。\n③卒業論文執筆の準備を始め、卒論プロポーザルを完成させる。",
    "overview": "前期は、主に教科書の輪読を通して国際政治経済学の理論や国際政治経済事象のとらえ方を理解する。後期は、まず学術的論文とは何かを説明し、その構造、作法など理解する。その後、受講生の研究関心の掘り起こし＋研究テーマの設定、論文で用いる仮説の設定、論文アウトラインの構築を行い、最終的には「卒論プロポーザル」を完成させる。",
    "corresponding_diploma_policies": [
        "経済経営学科DP1",
        "経済経営学科DP2",
        "経済経営学科DP3"
    ],
    "textbooks": [
        {
            "title": "国際政治経済学・入門（第3版）",
            "year": 2008,
            "author": "野林健・大芝亮・納家政嗣・山田敦・長尾悟",
            "publisher": "有斐閣アルマ",
            "price": null,
            "isbn": "978-4-641-12333-5",
            "available_on_campus": false
        }
    ],
    "reference_books": [],
    "notes_on_enrollment": {
        "required_courses": [],
        "recommended_courses": [],
        "brings": "配布資料、筆記用具、パソコンまたはタブレット",
        "other": "なし"
    },
    "evaluation_criteria": "【到達目標】の各項目について、課題の提出、議論への参加、講義内容の理解の程度等を総合的に評価する。",
    "evaluation_ratio": {
        "試験": 0,
        "小テスト": 0,
        "レポート": 40,
        "発表・実技": 40,
        "ポートフォリオ": 0,
        "その他": 20
    },
    "message_from_teachers": "国際政治経済環境の変化は、国内政治経済にも大きな影響を及ぼします。視野を世界に広げつつ、身近な問題を批判的に考察する力を育てていきましょう。\nゼミなので出席は当然と考えています。教科書熟読、報告資料の作成、議論の準備等の予習を十分に行って授業に臨んでください。授業後は、当日の議論の内容をまとめ、定着させてください。",
    "schedule": [
        {
            "session": "1",
            "content": "イントロダクション・オリエンテーション：ゼミの進め方、評価方法等の説明",
            "methods": [
                "演習"
            ],
            "teachers": [
                "岡本次郎"
            ]
        },
        {
            "session": "2",
            "content": "「なぜ？」という視点の重要性：日常生活から「なぜ？」を探してみよう、その答えを考えてみよう",
            "methods": [
                "演習"
            ],
            "teachers": [
                "岡本次郎"
            ]
        },
        {
            "session": "3",
            "content": "教科書輪読（１）＋議論：経済の論理と政治の論理、国際経済の論理と国際指示の論理、経済グローバル化と国家の相克",
            "methods": [
                "演習"
            ],
            "teachers": [
                "岡本次郎"
            ]
        },
        {
            "session": "4",
            "content": "教科書輪読（２）＋議論：国際政治経済の見方（リアリズムとリベラリズム）",
            "methods": [
                "演習"
            ],
            "teachers": [
                "岡本次郎"
            ]
        },
        {
            "session": "5",
            "content": "教科書輪読（３）＋議論：国際政治経済の見方（マルキシズムとコンストラクティビズム）",
            "methods": [
                "演習"
            ],
            "teachers": [
                "岡本次郎"
            ]
        },
        {
            "session": "6",
            "content": "教科書輪読（４）＋議論：東西冷戦と国際経済秩序の形成・維持",
            "methods": [
                "演習"
            ],
            "teachers": [
                "岡本次郎"
            ]
        },
        {
            "session": "7",
            "content": "教科書輪読（５）＋議論：貿易をめぐる政治と経済１（GATT体制と埋め込まれた自由主義、保護主義の政治経済）",
            "methods": [
                "演習"
            ],
            "teachers": [
                "岡本次郎"
            ]
        },
        {
            "session": "8",
            "content": "教科書輪読（５）＋議論：貿易をめぐる政治と経済２（WTO体制下のグローバル化と地域主義）",
            "methods": [
                "演習"
            ],
            "teachers": [
                "岡本次郎"
            ]
        },
        {
            "session": "9",
            "content": "教科書輪読（６）＋議論：金融グローバル化と国際政治経済（制度と規範、累積債務、通貨危機）",
            "methods": [
                "演習"
            ],
            "teachers": [
                "岡本次郎"
            ]
        },
        {
            "session": "10",
            "content": "教科書輪読（７）＋議論：国境を越える人の移動１（難民と移民）",
            "methods": [
                "演習"
            ],
            "teachers": [
                "岡本次郎"
            ]
        },
        {
            "session": "11",
            "content": "教科書輪読（８）＋議論：国境を越える人の移動２（日本への人の移動、少子高齢化と外国人労働者問題）",
            "methods": [
                "演習"
            ],
            "teachers": [
                "岡本次郎"
            ]
        },
        {
            "session": "12",
            "content": "教科書輪読（９）＋議論：途上国の経済発展と国際政治経済（新興独立国と国際援助体制、グローバル化と開発援助）",
            "methods": [
                "演習"
            ],
            "teachers": [
                "岡本次郎"
            ]
        },
        {
            "session": "13",
            "content": "教科書輪読（10）＋議論：経済成長、民主化・人権、国際政治（経済成長と民主化・人権保護の相関性？　普遍的人権とは何か？　内政不干渉原則と「保護する責任」）",
            "methods": [
                "演習"
            ],
            "teachers": [
                "岡本次郎"
            ]
        },
        {
            "session": "14",
            "content": "教科書輪読（11）＋議論：地球環境保護をめぐる国際政治経済（経済成長と環境破壊、先進国と途上国の対立、地球環境レジームの形成）",
            "methods": [
                "演習"
            ],
            "teachers": [
                "岡本次郎"
            ]
        },
        {
            "session": "15",
            "content": "前期のまとめと夏休み課題（書評執筆）の説明",
            "methods": [
                "演習"
            ],
            "teachers": [
                "岡本次郎"
            ]
        },
        {
            "session": "16",
            "content": "学術的論文とは何か？：学術的論文の目的と構造、因果関係の論証について",
            "methods": [
                "演習"
            ],
            "teachers": [
                "岡本次郎"
            ]
        },
        {
            "session": "17",
            "content": "文献・情報の検索の仕方：参考資料の見つけ方、統計データの見つけ方、学術論文を読む",
            "methods": [
                "演習"
            ],
            "teachers": [
                "岡本次郎"
            ]
        },
        {
            "session": "18",
            "content": "「コピペ」は不正か？：剽窃とは何か、剽窃はなぜしてはいけないのか、剽窃をしない論文の書き方",
            "methods": [
                "演習"
            ],
            "teachers": [
                "岡本次郎"
            ]
        },
        {
            "session": "19",
            "content": "（グループワーク）短い論文を書いて発表しよう（１）：論文テーマの設定",
            "methods": [
                "演習"
            ],
            "teachers": [
                "岡本次郎"
            ]
        },
        {
            "session": "20",
            "content": "（グループワーク）短い論文を書いて発表しよう（２）：論文の仮説の設定、問いと答えの因果関係の検討、議論",
            "methods": [
                "演習"
            ],
            "teachers": [
                "岡本次郎"
            ]
        },
        {
            "session": "21",
            "content": "（グループワーク）短い論文を書いて発表しよう（３）：アウトラインversion 1の構築＋議論",
            "methods": [
                "演習"
            ],
            "teachers": [
                "岡本次郎"
            ]
        },
        {
            "session": "22",
            "content": "（グループワーク）短い論文を書いて発表しよう（４）：アウトラインversion 2の構築＋議論",
            "methods": [
                "演習"
            ],
            "teachers": [
                "岡本次郎"
            ]
        },
        {
            "session": "23",
            "content": "（グループワーク）短い論文を書いて発表しよう（５）：論文version 1執筆＋議論",
            "methods": [
                "演習"
            ],
            "teachers": [
                "岡本次郎"
            ]
        },
        {
            "session": "24",
            "content": "（グループワーク）短い論文を書いて発表しよう（６）：論文の完成＋発表＋議論",
            "methods": [
                "演習"
            ],
            "teachers": [
                "岡本次郎"
            ]
        },
        {
            "session": "25",
            "content": "卒論プロポーザルを書こう（１）：個々人で自分の研究関心を考える、論文テーマの設定",
            "methods": [
                "演習"
            ],
            "teachers": [
                "岡本次郎"
            ]
        },
        {
            "session": "26",
            "content": "卒論プロポーザルを書こう（２）：論文の仮説の設定、問いと答えの因果関係の検討、議論",
            "methods": [
                "演習"
            ],
            "teachers": [
                "岡本次郎"
            ]
        },
        {
            "session": "27",
            "content": "卒論プロポーザルを書こう（３）：卒論アウトラインversion 1の作成＋議論",
            "methods": [
                "演習"
            ],
            "teachers": [
                "岡本次郎"
            ]
        },
        {
            "session": "28",
            "content": "卒論プロポーザルを書こう（４）：卒論アウトラインversion 2の作成＋議論",
            "methods": [
                "演習"
            ],
            "teachers": [
                "岡本次郎"
            ]
        },
        {
            "session": "29",
            "content": "卒論プロポーザルを書こう（５）：プロポーザルの完成",
            "methods": [
                "演習"
            ],
            "teachers": [
                "岡本次郎"
            ]
        },
        {
            "session": "30",
            "content": "全体のまとめ",
            "methods": [
                "演習"
            ],
            "teachers": [
                "岡本次郎"
            ]
        }
    ],
    "open_to_non_students": false,
    "practitioner": ""
}
