{
    "_fetched_at": "2024-08-07T16:33:26Z",
    "name_ja": "心理統計学",
    "name_en": "Psychology statistics",
    "syllabus_number": "2023600A",
    "course_number": "",
    "target_departments_and_courses": [
        "福祉情報学部"
    ],
    "type": "",
    "main_department": "",
    "requirements": "",
    "year": 2,
    "period": "",
    "required_or_elective": "※設定中",
    "course_category": "",
    "class_type": "単独",
    "teachers": [
        {
            "name": "阿部　夏希",
            "main": false
        }
    ],
    "term": "前期",
    "credits": 2,
    "teaching_methods": [
        "講義",
        "演習"
    ],
    "class_forms": [
        "オンライン"
    ],
    "themes_and_goals": "本授業の到達目標は以下の通りである。\n1. 心理学研究においてよく利用される基礎的な統計手法について，それらの概略を理解することができる。\n2. 必要に応じて基礎的な統計手法を使い分けることができる。\n3. 統計分析を行うために必要なソフトウェアを使用することができる。",
    "overview": "実証科学である心理学研究では，目に見えない心のはたらき（心理的構成概念）を測定するために実験や調査を行い，これを分析することによって人間の行動の背景に関する仮説や理論の正しさを主張する。心理統計学では，取得した①量的データを分析するための手法を学ぶほか，②統計学の基礎的知識を習得することを目指す。①の統計手法を学習する際は，データ分析のソフトの一つであるHADによる演習を行う。",
    "corresponding_diploma_policies": [
        "人間コミュニケーション学科DP1",
        "人間コミュニケーション学科DP2",
        "人間コミュニケーション学科DP3",
        "人間コミュニケーション学科DP4"
    ],
    "textbooks": [],
    "reference_books": [
        {
            "title": "Exelで今すぐはじめる心理統計　簡単ツールHADで基本を身につける",
            "year": 2018,
            "author": "小宮あすか・布井雅人",
            "publisher": "講談社",
            "price": 3080,
            "isbn": "4061548123",
            "available_on_campus": false
        },
        {
            "title": "よくわかる心理統計",
            "year": 2004,
            "author": "山田剛史・村井潤一郎",
            "publisher": "ミネルヴァ書房",
            "price": 2950,
            "isbn": "4623039994",
            "available_on_campus": false
        },
        {
            "title": "心理学のための統計学入門: ココロのデータ分析",
            "year": 2014,
            "author": "川端一光・荘島宏二郎",
            "publisher": "誠信書房",
            "price": 2310,
            "isbn": "4414301874",
            "available_on_campus": false
        }
    ],
    "notes_on_enrollment": {
        "required_courses": [
            "なし"
        ],
        "recommended_courses": [
            "なし"
        ],
        "brings": "Excelが入っているPC（可能な限りWindowsをおすすめします）",
        "other": ""
    },
    "evaluation_criteria": "授業への参加の度合い，課題への取り組み，課題の出来映えなどから総合的に判断するが目安としては以下のとおりである。\n\n到達目標1～3について，一定水準以上に達していると確認でき，かついずれかにおいて突出しているところがあると認められる場合　S\n到達目標1～3について，一定水準以上に達していると確認できる場合　A\n到達目標1～3について，一定水準に達していると確認できる場合　B\n到達目標1～3について，望ましい水準ではないが評価できると確認できる場合　C\n授業への参加度合いや提出物が不十分かつ到達目標に達していないと確認でき，評価できる条件を満たしていない場合　D　\n\n達成度は，授業ごとの小テスト（40％），中間テスト（10％），期末テスト（50％）から判断する。",
    "evaluation_ratio": {
        "試験": 60,
        "小テスト": 40,
        "レポート": 0,
        "発表・実技": 0,
        "ポートフォリオ": 0,
        "その他": 0
    },
    "message_from_teachers": "心理統計の知識とスキルは，授業時間だけでは決して身につきません。授業の事前・事後学修以外にも，参考書籍および自主学習教材等を活用して課外での自主学習に努めてください。",
    "schedule": [
        {
            "session": "1",
            "content": "【オリエンテーション：心理学と統計の関係性】\nオリエンテーションとして，授業の進め方や受講上の諸注意等について説明する。また，心理学になぜ統計が必要なのか簡単な例をもとに解説する。",
            "methods": [
                "講義"
            ],
            "teachers": [
                "阿部　夏希"
            ]
        },
        {
            "session": "2",
            "content": "【記述統計①：度数分布，ヒストグラム，代表値と散布度，分散，標準偏差】\nデータを集めたら，まずはその特徴を要約することが重要である。ここでは図表による要約と数値による要約の方法について演習を交えながら学ぶ。",
            "methods": [
                "講義",
                "演習"
            ],
            "teachers": [
                "阿部　夏希"
            ]
        },
        {
            "session": "3",
            "content": "【データの性質と尺度水準】\n一口に数値といっても，学生番号の235100と重さ235100kgでは数値の意味が全く異なる。このような数値の違いを尺度水準と呼ぶ。尺度水準は分析の仕方にも影響するものであり，データを扱う上での基本中の基本となることを学習する。",
            "methods": [
                "講義",
                "演習"
            ],
            "teachers": [
                "阿部　夏希"
            ]
        },
        {
            "session": "4",
            "content": "【記述統計②：クロス集計表、連関係数、散布図、共分散、相関係数】\n心理学の研究では，複数の変数の関係を考えることが一般的である。ここでは2つの変数の関係を記述する方法として，図表で表す方法と数値で表す方法を演習を行いながら学ぶ。",
            "methods": [
                "講義",
                "演習"
            ],
            "teachers": [
                "阿部　夏希"
            ]
        },
        {
            "session": "5",
            "content": "【標準化：標準得点，z得点，偏差値，標準偏差】\n平均や標準偏差が異なる変数を比較するための方法として，データの標準化について演習を交えて学ぶ。",
            "methods": [
                "講義",
                "演習"
            ],
            "teachers": [
                "阿部　夏希"
            ]
        },
        {
            "session": "6",
            "content": "【推測統計の基礎①：母集団，標本，確率変数，確率分布，標本統計量，母集団分布，標本分布，正規分布】\n心理学では得られたデータの特徴をわかりやすくまとめること以外に，手元にあるデータの背後にあるさらに大きな対象に当てはまるか否かを判断する際にも統計の手法が用いられる。この回では，推測統計の基本的な考え方について解説する。",
            "methods": [
                "講義",
                "演習"
            ],
            "teachers": [
                "阿部　夏希"
            ]
        },
        {
            "session": "7",
            "content": "【推測統計の基礎②：点推定，区間推定，信頼区間】\n前回に引き続き推測統計に関する基礎事項を解説すると共に，標本から母集団を推定する方法について概説する。",
            "methods": [
                "講義",
                "演習"
            ],
            "teachers": [
                "阿部　夏希"
            ]
        },
        {
            "session": "8",
            "content": "【統計的仮説検定：帰無仮説，対立仮説，有意水準，検定力，検定における2種類の誤り】\n「男女で自尊感情尺度の得点に差はあるのか」といったように，ある条件間で母集団の値に差があるかについて，統計的に検討する方法である統計的仮説検定について概説する。",
            "methods": [
                "講義",
                "演習"
            ],
            "teachers": [
                "阿部　夏希"
            ]
        },
        {
            "session": "9",
            "content": "【2つの平均値を比べる：対応のあるt検定と対応のないt検定】\n2つの平均値の差を比べるt検定の方法について，演習を交えて学ぶ",
            "methods": [
                "講義",
                "演習"
            ],
            "teachers": [
                "阿部　夏希"
            ]
        },
        {
            "session": "10",
            "content": "【分散分析①】\n１要因の分散分析，被験者間計画，多重比較について学習する。",
            "methods": [
                "講義",
                "演習"
            ],
            "teachers": [
                "阿部　夏希"
            ]
        },
        {
            "session": "11",
            "content": "【分散分析②】\n2要因の分散分析，主効果，交互作用について学習する。",
            "methods": [
                "講義",
                "演習"
            ],
            "teachers": [
                "阿部　夏希"
            ]
        },
        {
            "session": "12",
            "content": "【回帰分析①】\n回帰分析のなかでもごく基本的な分析である単回帰分析について学習する。",
            "methods": [
                "講義",
                "演習"
            ],
            "teachers": [
                "阿部　夏希"
            ]
        },
        {
            "session": "13",
            "content": "【回帰分析②】\n多変量解析の分析手法の1つである重回帰分析の考え方を理解することを目的とする。重回帰分析，標準偏回帰係数，重相関係数，決定係数，パス図について学習する。",
            "methods": [
                "講義",
                "演習"
            ],
            "teachers": [
                "阿部　夏希"
            ]
        },
        {
            "session": "14",
            "content": "【因子分析】\n多変量解析の分析手法の1つである因子分析の考え方を理解する。",
            "methods": [
                "講義",
                "演習"
            ],
            "teachers": [
                "阿部　夏希"
            ]
        },
        {
            "session": "15",
            "content": "【総括】\nこれまでに学習した内容を振り返り、心理学統計についての理解の定着を目指す。",
            "methods": [
                "講義",
                "演習"
            ],
            "teachers": [
                "阿部　夏希"
            ]
        }
    ],
    "open_to_non_students": false,
    "practitioner": ""
}
