{
    "_fetched_at": "2024-08-07T17:03:19Z",
    "name_ja": "マクロ経済学Ⅰ",
    "name_en": "Macroeconomics Ⅰ",
    "syllabus_number": "2034200A",
    "course_number": "a",
    "target_departments_and_courses": [
        "経済学部"
    ],
    "type": "専門科目",
    "main_department": "",
    "requirements": "",
    "year": 2,
    "period": "",
    "required_or_elective": "※設定中",
    "course_category": "",
    "class_type": "クラス分け",
    "teachers": [
        {
            "name": "長澤　賢一",
            "main": true
        },
        {
            "name": "田尾　真一",
            "main": false
        }
    ],
    "term": "前期",
    "credits": 2,
    "teaching_methods": [
        "講義"
    ],
    "class_forms": [
        "対面"
    ],
    "themes_and_goals": "【到達目標】\n（１）マクロ経済に関する基本的な考え方について理解できる。\n（２）マクロ経済学に関する計算問題を解答できるようにする。",
    "overview": "マクロ経済学とは、所得、物価、雇用、経済成長など、経済全体にかかわる大きな問題を分析する学問である。本講義では、ＧＤＰ、家計や企業の行動、総需要管理政策、財政・金融政策の概念など、マクロ経済学の基礎的な概念を学習し、マクロ経済の状況が、我々の日常生活にもたらす影響を説明する。本講義を通じて、日本政府が公表するマクロ経済指標やその概念について、より深く理解することを目指す。なお、本講義では計算演習を積極的に取り入れていく。",
    "corresponding_diploma_policies": [
        "現代経済学科DP1",
        "現代経済学科DP2",
        "経済経営学科DP2",
        "経済経営学科DP3"
    ],
    "textbooks": [
        {
            "title": "マクロ経済学の基礎(第2版)",
            "year": 2021,
            "author": "家森信繁",
            "publisher": "中央経済社",
            "price": 2200,
            "isbn": "978-4-502-37131-8",
            "available_on_campus": true
        }
    ],
    "reference_books": [
        {
            "title": "マクロ経済学(第2版)",
            "year": 2012,
            "author": "伊藤元重",
            "publisher": "日本評論社",
            "price": 3080,
            "isbn": "978-4535556218",
            "available_on_campus": false
        }
    ],
    "notes_on_enrollment": {
        "required_courses": [
            "なし"
        ],
        "recommended_courses": [
            "マクロ経済学Ⅱ",
            "ミクロ経済学Ⅰ",
            "ミクロ経済学Ⅱ",
            "金融論",
            "財政論"
        ],
        "brings": "テキスト、必要に応じて電卓",
        "other": "経済学部2021年度以前入学の学生は、「マクロ経済学Ⅰ」及び「マクロ経済学Ⅱ」の両方の単位を修得することで、「マクロ経済学（４単位）」の単位が修得できます。"
    },
    "evaluation_criteria": "マクロ経済に関する基本的な考え方についての理解度を評価する（最終テスト：60％、中間テスト：40％）",
    "evaluation_ratio": {
        "試験": 0,
        "小テスト": 100,
        "レポート": 0,
        "発表・実技": 0,
        "ポートフォリオ": 0,
        "その他": 0
    },
    "message_from_teachers": "マクロ経済学を学ぶことで現実の経済問題への理解が深まり、日本経済新聞などの経済ニュースの理解が深まります。本講義を受ける前と後においては、テキストを熟読してください（1～2時間程度）。",
    "schedule": [
        {
            "session": "１",
            "content": "イントロダクション／マクロ経済学を学ぶことの意義",
            "methods": [
                "講義"
            ],
            "teachers": [
                "長澤　賢一",
                "田尾　真一"
            ]
        },
        {
            "session": "２",
            "content": "マクロ経済学と日本経済",
            "methods": [
                "講義"
            ],
            "teachers": [
                "長澤　賢一",
                "田尾　真一"
            ]
        },
        {
            "session": "3",
            "content": "ＧＤＰについて①／ＧＤＰの基礎的な概念",
            "methods": [
                "講義"
            ],
            "teachers": [
                "長澤　賢一",
                "田尾　真一"
            ]
        },
        {
            "session": "４",
            "content": "ＧＤＰについて②／ＧＤＰの三面等価、ＧＤＰギャップ",
            "methods": [
                "講義"
            ],
            "teachers": [
                "長澤　賢一",
                "田尾　真一"
            ]
        },
        {
            "session": "５",
            "content": "ＧＤＰについて③／経済成長と景気循環",
            "methods": [
                "講義"
            ],
            "teachers": [
                "長澤　賢一",
                "田尾　真一"
            ]
        },
        {
            "session": "６",
            "content": "消費と貯蓄／消費関数、日本の消費関数など",
            "methods": [
                "講義"
            ],
            "teachers": [
                "長澤　賢一",
                "田尾　真一"
            ]
        },
        {
            "session": "７",
            "content": "企業の投資／投資関数、日本の投資関数など",
            "methods": [
                "講義"
            ],
            "teachers": [
                "長澤　賢一",
                "田尾　真一"
            ]
        },
        {
            "session": "８",
            "content": "政府の支出①／財政政策、財政の役割",
            "methods": [
                "講義"
            ],
            "teachers": [
                "長澤　賢一",
                "田尾　真一"
            ]
        },
        {
            "session": "９",
            "content": "政府の支出②／日本の財政状況（国債発行と財政赤字）",
            "methods": [
                "講義"
            ],
            "teachers": [
                "長澤　賢一",
                "田尾　真一"
            ]
        },
        {
            "session": "１０",
            "content": "小テスト、解答と解説講義",
            "methods": [
                "講義"
            ],
            "teachers": [
                "長澤　賢一",
                "田尾　真一"
            ]
        },
        {
            "session": "１１",
            "content": "総需要管理政策①／有効需要の原理、45度線分析",
            "methods": [
                "講義"
            ],
            "teachers": [
                "長澤　賢一",
                "田尾　真一"
            ]
        },
        {
            "session": "１２",
            "content": "総需要管理政策②／乗数理論、計算演習",
            "methods": [
                "講義"
            ],
            "teachers": [
                "長澤　賢一",
                "田尾　真一"
            ]
        },
        {
            "session": "１３",
            "content": "金融市場の分析①／貨幣の役割、信用創造の概念、貨幣需要と貨幣供給",
            "methods": [
                "講義"
            ],
            "teachers": [
                "長澤　賢一",
                "田尾　真一"
            ]
        },
        {
            "session": "１４",
            "content": "金融市場の分析②／中央銀行の役割とマクロ金融政策",
            "methods": [
                "講義"
            ],
            "teachers": [
                "長澤　賢一",
                "田尾　真一"
            ]
        },
        {
            "session": "１５",
            "content": "テスト、講義の総括と振り返り",
            "methods": [
                "講義"
            ],
            "teachers": [
                "長澤　賢一",
                "田尾　真一"
            ]
        }
    ],
    "open_to_non_students": true,
    "practitioner": "この講座を担当する実務家教員（長澤賢一）の職歴\n【職歴】\n・1992年～2022年、財務省で勤務。主に、証券取引等監視委員会、財務省関東財務局において、金融商品取引業者の検査、監督業務に従事しており、実務経験を踏まえた講義を行う。"
}
