{
    "_fetched_at": "2024-08-07T17:09:13Z",
    "name_ja": "地域福祉キャリア形成活動Ⅰ",
    "name_en": "Community Welfare Career Development Activity I.",
    "syllabus_number": "2123200A",
    "course_number": "a",
    "target_departments_and_courses": [
        "人間健康学部 福祉学科"
    ],
    "type": "専門科目",
    "main_department": "",
    "requirements": "",
    "year": 1,
    "period": "",
    "required_or_elective": "※設定中",
    "course_category": "",
    "class_type": "複数",
    "teachers": [
        {
            "name": "小林　武生",
            "main": true
        },
        {
            "name": "牛島　豊広",
            "main": false
        },
        {
            "name": "金子　幸",
            "main": false
        },
        {
            "name": "北村　光子",
            "main": false
        },
        {
            "name": "伊藤　敏安",
            "main": false
        },
        {
            "name": "梅田　勝利",
            "main": false
        }
    ],
    "term": "後期",
    "credits": 2,
    "teaching_methods": [
        "実験・実習・実技"
    ],
    "class_forms": [
        "対面"
    ],
    "themes_and_goals": "①社会人に求められるソーシャルスキルについて説明することができる。 \n②今後のキャリア選択肢について説明することができる。 \n③子ども、高齢者や障害のある方と関わり、支援の基盤となるコミュニケーションスキルについて説明することができる。",
    "overview": "授業では、社会人基礎力の育成、社会人としての職業観の涵養、社会福祉事業・施設の理解、子ども、高齢者や障害のある方との関係構築について学び、活動を行う施設の職員、学生、担当教員の三者で協議したプログラムを実施・体験していく。",
    "corresponding_diploma_policies": [
        "福祉学科DP2"
    ],
    "textbooks": [
        {
            "title": "適宜、必要な資料を配布、もしくは紹介する。",
            "year": 0,
            "author": "",
            "publisher": "",
            "price": null,
            "isbn": "",
            "available_on_campus": false
        }
    ],
    "reference_books": [
        {
            "title": "適宜、必要な資料を配布、もしくは紹介する。",
            "year": 0,
            "author": "",
            "publisher": "",
            "price": null,
            "isbn": "",
            "available_on_campus": false
        }
    ],
    "notes_on_enrollment": {
        "required_courses": [
            "地域福祉キャリア形成活動指導Ⅰ"
        ],
        "recommended_courses": [],
        "brings": "",
        "other": "なし"
    },
    "evaluation_criteria": "①社会人に求められるソーシャルスキル \n②今後のキャリアの選択肢 \n③子ども、高齢者や障害のある方とのコミュニケーションスキル",
    "evaluation_ratio": {
        "試験": 0,
        "小テスト": 0,
        "レポート": 75,
        "発表・実技": 0,
        "ポートフォリオ": 0,
        "その他": 25
    },
    "message_from_teachers": "学外での実習が中心となる。実習では、周南公立大学の学生として、責任を持ち、積極的な行動をとることが求められる。また、社会福祉の現場を知ることはもちろん、礼儀作法やビジネスマナーもしっかり身に付けるように取り組むこと。実習に参加するにあたっては、実習施設から指示される課題に加え、その周辺領域の学びに取り組む必要がある。",
    "schedule": [
        {
            "session": "1",
            "content": "実習先での活動",
            "methods": [
                "実験・実習・実技"
            ],
            "teachers": [
                "小林武生",
                "牛島豊広",
                "金子幸",
                "北村光子",
                "伊藤敏安",
                "梅田勝利"
            ]
        },
        {
            "session": "2",
            "content": "実習先での活動",
            "methods": [
                "実験・実習・実技"
            ],
            "teachers": [
                "小林武生",
                "牛島豊広",
                "金子幸",
                "北村光子",
                "伊藤敏安",
                "梅田勝利"
            ]
        },
        {
            "session": "3",
            "content": "実習先での活動",
            "methods": [
                "実験・実習・実技"
            ],
            "teachers": [
                "小林武生",
                "牛島豊広",
                "金子幸",
                "北村光子",
                "伊藤敏安",
                "梅田勝利"
            ]
        },
        {
            "session": "4",
            "content": "実習先での活動",
            "methods": [
                "実験・実習・実技"
            ],
            "teachers": [
                "小林武生",
                "牛島豊広",
                "金子幸",
                "北村光子",
                "伊藤敏安",
                "梅田勝利"
            ]
        },
        {
            "session": "5",
            "content": "実習先での活動",
            "methods": [
                "実験・実習・実技"
            ],
            "teachers": [
                "小林武生",
                "牛島豊広",
                "金子幸",
                "北村光子",
                "伊藤敏安",
                "梅田勝利"
            ]
        },
        {
            "session": "6",
            "content": "実習先での活動",
            "methods": [
                "実験・実習・実技"
            ],
            "teachers": [
                "小林武生",
                "牛島豊広",
                "金子幸",
                "北村光子",
                "伊藤敏安",
                "梅田勝利"
            ]
        },
        {
            "session": "7",
            "content": "実習先での活動",
            "methods": [
                "実験・実習・実技"
            ],
            "teachers": [
                "小林武生",
                "牛島豊広",
                "金子幸",
                "北村光子",
                "伊藤敏安",
                "梅田勝利"
            ]
        },
        {
            "session": "8",
            "content": "実習先での活動",
            "methods": [
                "実験・実習・実技"
            ],
            "teachers": [
                "小林武生",
                "牛島豊広",
                "金子幸",
                "北村光子",
                "伊藤敏安",
                "梅田勝利"
            ]
        },
        {
            "session": "9",
            "content": "実習先での活動",
            "methods": [
                "実験・実習・実技"
            ],
            "teachers": [
                "小林武生",
                "牛島豊広",
                "金子幸",
                "北村光子",
                "伊藤敏安",
                "梅田勝利"
            ]
        },
        {
            "session": "10",
            "content": "実習先での活動",
            "methods": [
                "実験・実習・実技"
            ],
            "teachers": [
                "小林武生",
                "牛島豊広",
                "金子幸",
                "北村光子",
                "伊藤敏安",
                "梅田勝利"
            ]
        },
        {
            "session": "11",
            "content": "実習先での活動",
            "methods": [
                "実験・実習・実技"
            ],
            "teachers": [
                "小林武生",
                "牛島豊広",
                "金子幸",
                "北村光子",
                "伊藤敏安",
                "梅田勝利"
            ]
        },
        {
            "session": "12",
            "content": "実習先での活動",
            "methods": [
                "実験・実習・実技"
            ],
            "teachers": [
                "小林武生",
                "牛島豊広",
                "金子幸",
                "北村光子",
                "伊藤敏安",
                "梅田勝利"
            ]
        },
        {
            "session": "13",
            "content": "実習先での活動",
            "methods": [
                "実験・実習・実技"
            ],
            "teachers": [
                "小林武生",
                "牛島豊広",
                "金子幸",
                "北村光子",
                "伊藤敏安",
                "梅田勝利"
            ]
        },
        {
            "session": "14",
            "content": "実習先での活動",
            "methods": [
                "実験・実習・実技"
            ],
            "teachers": [
                "小林武生",
                "牛島豊広",
                "金子幸",
                "北村光子",
                "伊藤敏安",
                "梅田勝利"
            ]
        },
        {
            "session": "15",
            "content": "実習先での活動",
            "methods": [
                "実験・実習・実技"
            ],
            "teachers": [
                "小林武生",
                "牛島豊広",
                "金子幸",
                "北村光子",
                "伊藤敏安",
                "梅田勝利"
            ]
        }
    ],
    "open_to_non_students": false,
    "practitioner": ""
}
