{
    "_fetched_at": "2024-08-07T17:10:55Z",
    "name_ja": "特別活動および総合的な学習の時間",
    "name_en": "Special Activities the Period for Integrated Studies",
    "syllabus_number": "7002510A",
    "course_number": "",
    "target_departments_and_courses": [
        "経済学部",
        "福祉情報学部"
    ],
    "type": "",
    "main_department": "",
    "requirements": "",
    "year": 3,
    "period": "",
    "required_or_elective": "※設定中",
    "course_category": "",
    "class_type": "単独",
    "teachers": [
        {
            "name": "石橋　孝明",
            "main": false
        }
    ],
    "term": "前期",
    "credits": 2,
    "teaching_methods": [
        "講義",
        "演習"
    ],
    "class_forms": [
        "対面"
    ],
    "themes_and_goals": "【到達目標】\n(ⅰ)特別活動の意義、目標及び内容を説明することができる。\n(ⅱ)特別活動の指導の在り方を説明することができる。\n(ⅲ)総合的な学習の時間の意義や各学校において目標及び内容を定める際の考え方を説明することができる。\n(ⅳ)総合的な学習の時間の指導計画作成の考え方を理解し、その実現のために必要な基礎的な能力を身に付ける。\n(ⅴ)総合的な学習の時間の指導と評価の考え方および実践上の留意点を説明することができる。",
    "overview": "特別活動は、学校における様々な構成の集団での活動を通して、課題の発見や解決を行い、よりよい集団や学校生活を目指して様々に行われる活動の総体である。学校教育全体における特別活動の意義を理解し、「人間関係形成」・「社会参画」・「自己実現」の三つの視点や「チームとしての学校」の視点を持つとともに、学年の違いによる活動の変化、各教科等との往還的な関連、地域住民や他校の教職員と連携した組織的な対応等の特別活動の特質を踏まえた指導に必要な知識や素養を身に付ける。\n総合的な学習の時間は、探究的な見方・考え方を働かせ、横断的・総合的な学習を行うことを通して、よりよく課題を解決し、自己の生き方を考えていくための資質・能力の育成を目指す。\n各教科等で育まれる見方・考え方を総合的に活用して、広範な事象を多様な角度から俯瞰して促え、実社会・実生活の課題を探究する学びを実現するために、指導計画の作成および具体的な指導の仕方、並びに学習活動の評価に関する知識・技能を身に付ける。",
    "corresponding_diploma_policies": [],
    "textbooks": [
        {
            "title": "中学校学習指導要領（平成 29 年告示）解説　特別活動編",
            "year": 2019,
            "author": "文部科学省",
            "publisher": "東山書房",
            "price": 303,
            "isbn": "978-4-8278-1578-8",
            "available_on_campus": false
        },
        {
            "title": "中学校学習指導要領（平成 29 年告示）解説　総合的な学習の時間編",
            "year": 2019,
            "author": "文部科学省",
            "publisher": "東山書房",
            "price": 230,
            "isbn": "978-4-8278-1561-0",
            "available_on_campus": false
        },
        {
            "title": "高等学校学習指導要領（平成 30 年告示）解説　特別活動編",
            "year": 2019,
            "author": "文部科学省",
            "publisher": "東京書籍",
            "price": 990,
            "isbn": "978-4-4872-8635-5",
            "available_on_campus": false
        },
        {
            "title": "高等学校学習指導要領（平成 30 年告示）解説　総合的な探求の時間編",
            "year": 2019,
            "author": "文部科学省",
            "publisher": "学校図書",
            "price": 297,
            "isbn": "978-4-7625-0536-2",
            "available_on_campus": false
        }
    ],
    "reference_books": [
        {
            "title": "中学校学習指導要領（平成 29 年告示）解説　総則編",
            "year": 2019,
            "author": "文部科学省",
            "publisher": "東山書房",
            "price": 397,
            "isbn": "978-4-8278-1579-5",
            "available_on_campus": false
        },
        {
            "title": "高等学校学習指導要領（平成 30 年告示）解説　総則編",
            "year": 2019,
            "author": "文部科学省",
            "publisher": "東山書房",
            "price": 834,
            "isbn": "978-4-8278-1562-2",
            "available_on_campus": false
        }
    ],
    "notes_on_enrollment": {
        "required_courses": [
            "教師論",
            "教育課程論"
        ],
        "recommended_courses": [
            "教育原理",
            "教育心理学",
            "教育相談Ⅰ、Ⅱ",
            "道徳教育",
            "生徒指導論"
        ],
        "brings": "教科書、ノート、筆記用具",
        "other": "なし"
    },
    "evaluation_criteria": "(ⅰ) 特別活動の意義、目標及び内容の理解、(ⅱ) 特別活動の指導の在り方の理解、(ⅲ) 総合的な学習の時間の意義、目標及び内容の理解、(ⅳ)総合的な学習の時間の指導のあり方の理解、基礎的な能力の養成、(ⅴ)総合的な学習の時間の指導、評価、実践上の留意点の理解 の五点を⑪に示す方法で評価する。",
    "evaluation_ratio": {
        "試験": 60,
        "小テスト": 0,
        "レポート": 0,
        "発表・実技": 40,
        "ポートフォリオ": 0,
        "その他": 0
    },
    "message_from_teachers": "教科書に即しながら授業を進める。基本的には講義形式で行うが、一部グループワークを取り入れる。そして、必要に応じてプリントを配布する。授業計画は、進行状況・問題への関心等に応じて、一部変更することがある。教師になることを目指す以上、その自覚をもって受講すること。\n授業並びに本学のEQ教育やキャリア教育を活かし特別活動の指導ができる教員になってください。\n\n【予習・復習について】\n授業計画で各回の講義内容に該当する教科書に目を通しておくこと。その他適宜指示をする(30～90分程度)。",
    "schedule": [
        {
            "session": "1",
            "content": "オリエンテーション：\n特別活動とは何かについて考える\n特別活動の目標：目標、基本的な性格と教育活動全体における意義について考える（理論編）",
            "methods": [
                "講義",
                "演習"
            ],
            "teachers": [
                "石橋　孝明"
            ]
        },
        {
            "session": "2",
            "content": "各活動・学校行事の目標と内容（１）：学級活動・ホームルーム活動、（２）生徒会活動、（３）学校行事について考える（理論編）",
            "methods": [
                "講義",
                "演習"
            ],
            "teachers": [
                "石橋　孝明"
            ]
        },
        {
            "session": "3",
            "content": "指導計画の作成と内容の取扱い（１）：指導計画の作成に当たっての配慮事項、内容の取扱いについての配慮事項について考える、（２）国旗・国家の取扱い、担当教師、評価について考える（理論編）",
            "methods": [
                "講義",
                "演習"
            ],
            "teachers": [
                "石橋　孝明"
            ]
        },
        {
            "session": "4",
            "content": "指導計画を作成する：（１）全体計画を作\n成する、（２）各活動の年間指導計画を作成する、（３）学級活動もしくはホームルーム活動の１単位時間の指導計画を作成する（実践編）",
            "methods": [
                "講義",
                "演習"
            ],
            "teachers": [
                "石橋　孝明"
            ]
        },
        {
            "session": "5",
            "content": "指導計画を作成する：（４）生徒会活動の１単位時間の指導計画を作成する、（５）学校行事の６単位時間の指導計画を作成する（実践編）",
            "methods": [
                "講義",
                "演習"
            ],
            "teachers": [
                "石橋　孝明"
            ]
        },
        {
            "session": "6",
            "content": "学級活動の発表（指導計画案の代表例の発表（パワーポイント使用））(実践編）",
            "methods": [
                "講義",
                "演習"
            ],
            "teachers": [
                "石橋　孝明"
            ]
        },
        {
            "session": "7",
            "content": "学校行事の発表（指導計画案の代表例の発表（パワーポイント使用））（実践編）",
            "methods": [
                "講義",
                "演習"
            ],
            "teachers": [
                "石橋　孝明"
            ]
        },
        {
            "session": "8",
            "content": "総合的な学習の時間とは何か\n総合的な学習の時間の意義と教育課程において果たす役割、目標並びに各学校において目標及び内容を定める際の考え方や留意点について考える（理論編）",
            "methods": [
                "講義",
                "演習"
            ],
            "teachers": [
                "石橋　孝明"
            ]
        },
        {
            "session": "9",
            "content": "総合的な学習の時間の指導計画作成について考える（年間指導計画と単元計画）（理論編）",
            "methods": [
                "講義",
                "演習"
            ],
            "teachers": [
                "石橋　孝明"
            ]
        },
        {
            "session": "10",
            "content": "総合的な学習の時間の指導と評価の考え方および実践上の留意点について（理論編）",
            "methods": [
                "講義",
                "演習"
            ],
            "teachers": [
                "石橋　孝明"
            ]
        },
        {
            "session": "11",
            "content": "指導の留意点と評価の方法を考慮した、総合的な学習時間の年間指導計画（及び単元計画）を作成する（実践編）",
            "methods": [
                "講義",
                "演習"
            ],
            "teachers": [
                "石橋　孝明"
            ]
        },
        {
            "session": "12",
            "content": "指導の留意点と評価の方法を考慮した、総合的な学習時間の年間指導計画（及び単元計画）を作成する（実践編）",
            "methods": [
                "講義",
                "演習"
            ],
            "teachers": [
                "石橋　孝明"
            ]
        },
        {
            "session": "13",
            "content": "総合的な学習の時間の年間指導計画の発表（パワーポイント使用）（実践編）",
            "methods": [
                "講義",
                "演習"
            ],
            "teachers": [
                "石橋　孝明"
            ]
        },
        {
            "session": "14",
            "content": "総合的な学習の時間の単元計画の発表（パワーポイント使用）（実践編）",
            "methods": [
                "講義",
                "演習"
            ],
            "teachers": [
                "石橋　孝明"
            ]
        },
        {
            "session": "15",
            "content": "全体の振り返りとまとめ：授業全体のポイントを確認する\n※オンライン授業評価に回答。\n※試験期間中に最終試験を実施します。",
            "methods": [
                "講義",
                "演習"
            ],
            "teachers": [
                "石橋　孝明"
            ]
        }
    ],
    "open_to_non_students": false,
    "practitioner": ""
}
